[
  {
    "id": "1770969194921",
    "companyName": "上海繇远",
    "companyInfo": {
      "name": "上海繇远",
      "shortName": "繇远",
      "slogan": "创新驱动，服务未来",
      "business": "上海繇远是一家专注于城市发展与科技创新的企业，核心业务涉及城市智能化解决方案、金融科技服务及文化旅游产业开发。公司致力于通过技术创新提升城市运营效率，为上海及周边地区提供综合性的发展支持，助力城市经济与社会的可持续发展。",
      "description": "上海繇远是一家立足于上海的企业，依托上海作为全球金融中心和亚洲重要城市的区位优势，专注于城市智能化、金融科技和文化旅游等领域的创新服务。公司结合上海的历史底蕴和现代发展，提供从城市基础设施优化到数字化解决方案的全方位服务。在业务实践中，繇远注重科技与人文的融合，推动城市向更高效、更宜居的方向发展。公司积极参与上海的城市建设，如支持旅游自由行试点等项目，同时探索在游戏和娱乐产业中的跨界合作，以多元化业务模式适应市场变化。繇远以客户为中心，致力于成为上海乃至亚洲地区领先的城市服务提供商，通过创新驱动，为城市未来注入活力。",
      "industry": "城市服务与科技创新",
      "founded": "2020年",
      "headquarters": "上海市",
      "services": [
        {
          "name": "城市智能化解决方案",
          "description": "提供基于大数据和人工智能的城市管理服务，优化交通、能源和公共安全等系统。"
        },
        {
          "name": "金融科技服务",
          "description": "开发金融科技产品，支持上海作为金融中心的数字化升级，包括支付系统和风险管理。"
        },
        {
          "name": "文化旅游产业开发",
          "description": "策划和执行文化旅游项目，如上海景点推广和自由行服务，提升城市文化吸引力。"
        }
      ],
      "features": [
        "依托上海区位优势，服务全球市场",
        "注重科技创新与城市发展融合",
        "多元化业务模式，涵盖智能、金融和文化领域"
      ],
      "contact": {
        "phone": "021-12345678",
        "email": "contact@shanghaiyaoyuan.com",
        "address": "上海市浦东新区某商务区"
      },
      "social": {
        "website": "https://www.shanghaiyaoyuan.com",
        "weibo": "https://weibo.com/shanghaiyaoyuan",
        "wechat": "上海繇远官方"
      }
    },
    "deployTarget": "qiniu",
    "previewUrl": "http://192.168.1.51:3000/preview/上海繇远-f7bd4278/",
    "indexUrl": "https://cdn2.xdbin.com/上海繇远-f7bd4278/index.html",
    "qiniuDir": "上海繇远-f7bd4278",
    "createdAt": "2026-02-13T07:53:14.923Z",
    "updatedAt": "2026-02-13T07:53:14.923Z"
  }
]